promptql_api_sdk/__init__.py
promptql_api_sdk/client.py
promptql_api_sdk/exceptions.py
promptql_api_sdk/types/__init__.py
promptql_api_sdk/types/models.py
promptql_api_sdk-0.1.1.dist-info/LICENSE
promptql_api_sdk-0.1.1.dist-info/METADATA
promptql_api_sdk-0.1.1.dist-info/WHEEL
promptql_api_sdk-0.1.1.dist-info/RECORD
