Metadata-Version: 2.3
Name: promptql-api-sdk
Version: 0.1.1
Summary: Python SDK for PromptQL Natural Language API
License: MIT
Keywords: promptql,api,sdk,hasura,llm,ai
Author: Hasura Team
Requires-Python: >=3.9
Classifier: Development Status :: 4 - Beta
Classifier: Intended Audience :: Developers
Classifier: License :: OSI Approved :: MIT License
Classifier: Programming Language :: Python :: 3
Classifier: Programming Language :: Python :: 3.9
Classifier: Programming Language :: Python :: 3.10
Classifier: Programming Language :: Python :: 3.11
Classifier: Programming Language :: Python :: 3.12
Classifier: Topic :: Software Development :: Libraries :: Python Modules
Requires-Dist: pydantic (>=2.0.0)
Requires-Dist: requests (>=2.25.0)
Requires-Dist: typing-extensions (>=4.0.0)
Project-URL: Documentation, https://hasura.io/docs/promptql/promptql-apis/natural-language-api/
Project-URL: Repository, https://github.com/hasura/promptql-python-sdk
